debug_mgr/__build_num__.py
debug_mgr/__init__.py
debug_mgr/core.cp310-win_amd64.pyd
debug_mgr/debug-mgr.dll
debug_mgr/debug-mgr.lib
debug_mgr/pkginfo.py
debug_mgr/share/include/dmgr/FactoryExt.h
debug_mgr/share/include/dmgr/IDebug.h
debug_mgr/share/include/dmgr/IDebugMgr.h
debug_mgr/share/include/dmgr/IDebugOut.h
debug_mgr/share/include/dmgr/IDebugOutList.h
debug_mgr/share/include/dmgr/IFactory.h
debug_mgr/share/include/dmgr/impl/DebugMacros.h
debug_mgr-0.0.2.9196773628.dist-info/LICENSE
debug_mgr-0.0.2.9196773628.dist-info/METADATA
debug_mgr-0.0.2.9196773628.dist-info/WHEEL
debug_mgr-0.0.2.9196773628.dist-info/entry_points.txt
debug_mgr-0.0.2.9196773628.dist-info/top_level.txt
debug_mgr-0.0.2.9196773628.dist-info/RECORD
