Metadata-Version: 2.1
Name: debug-mgr
Version: 0.0.2.9196773628
Summary: Simple debug manager for use of C++ Python extensions
Home-page: https://github.com/mballance/debug-mgr
Author: Matthew Ballance
Author-email: matt.ballance@gmail.com
License: Apache 2.0
Keywords: Debug,C/C++,Python
License-File: LICENSE
